enthusiast_model_google/__init__.py
enthusiast_model_google/embedding.py
enthusiast_model_google/language_model.py
enthusiast_model_google-1.2.0.dist-info/METADATA
enthusiast_model_google-1.2.0.dist-info/WHEEL
enthusiast_model_google-1.2.0.dist-info/RECORD
