Metadata-Version: 2.4
Name: enthusiast-model-google
Version: 1.2.0
Summary: A plugin for Enthusiast that provides a Google Gemini connector.
Author: Damian Sowiński
Author-email: damian.sowinski@upsidelab.io
Requires-Python: >=3.10,<4.0
Classifier: Programming Language :: Python :: 3
Classifier: Programming Language :: Python :: 3.10
Classifier: Programming Language :: Python :: 3.11
Classifier: Programming Language :: Python :: 3.12
Classifier: Programming Language :: Python :: 3.13
Classifier: Programming Language :: Python :: 3.14
Requires-Dist: enthusiast-common (>=1,<2)
Requires-Dist: google-genai (==1.18.0)
Requires-Dist: langchain-core (>=0.3.66,<1)
Requires-Dist: langchain-google-genai (>=2.1.5,<3.0.0)
